Workbook

Sheet Summary
B2: ITEMS - On Premise | C2: Price (RM)
B4: A. License
B5: Total License | C5: ='Lic-Misc'!#REF! -> #REF!
B7: B. Implementation Services
B8: =#REF! -> #REF! | C8: =#REF! -> #REF! | F8: =SUM(C8:E8) -> #REF!
B9: Total License And Implementation Services | C9: =C5+C8 -> #REF! | F9: =SUM(C9:E9) -> #REF!
B10: Support & Maintenance | C10: =Support!#REF! -> #REF! | F10: =SUM(C10:E10) -> #REF!
B11: Total License, Implementation Services & Support | C11: =C8+C5+C10 -> #REF!
B12: Total Year cost (Implementation, License & support) | C12: =C11 -> #REF!
B13: SST | C13: =(C12)*0.08 -> #REF!
B14: Grand Total | C14: =C12+C13 -> #REF!
B16: ITEMS | C16: Quantity | D16: Unit Price | E16: Total Price (RM)
B17: A. License | E17: =SUM(E18:E20) -> 0
B18: UiPath- Attended Robot | C18: 1 | D18: ='Lic-UiPath'!L11 -> 0 | E18: =C18*D18 -> 0
B19: UiPath Unattended Robot | C19: 1 | D19: ='Lic-Misc'!G5 -> 0 | E19: ='Lic-Misc'!I5 -> 0
B22: B. Implementation Services | E22: =SUM(E23:E25) -> 0 | F22: =E22*1.08 -> 0
B23: ='Project Cost-01'!C1 -> Automation of WTD | E23: ='Project Cost-01'!D$17 -> 0
B24: Automation of Biz & eBiz Account Opening
B27: C. Support & Maintenance | E27: =SUM(E28:E29) -> 0
B28: Basic Support
B29: Managed Services
B31: D. Infrastructure | E31: =SUM(E32:E33) -> 0
B32: Cloud Infrastucture - Virtual Machine | E32: =Hardware!I7 -> 0
B33: Others
B35: Total License, Implementation Services & Support | E35: =SUM(E17,E22,E27) -> 0
B36: Sales & Service tax SST 8% | E36: =E35*0.08 -> 0
B37: Grand Total | E37: =SUM(E35:E36) -> 0
B40: Note
B41: 1.The prices quoted above are valid for 30 days. Thereafter, subject to change without prior notice.
B42: 2.The Price quoted above does not include printing cost of any deliverable materials/documents as our new policy on the ESG
B43: 3. All price subject to Government tax guideline and subject to change according.
B44: 4. Payment is upon confirmation of each milestone

Sheet Project Prof
B2: Project Profitability
C3: Budgetary
B4: Revenue | C4: RM
B5: Implementation Cost 1 | C5: ='Project Cost-01'!D17 -> 0
B6: UiPath License Cost | C6: ='Lic-UiPath'!L11 -> 0
B7: Microsoft License Cost | C7: ='Lic-Misc'!I11 -> 0
B8: Cyclone License Cost | C8: ='Lic-Cyc'!I11 -> 0
B9: Other License | C9: =ROUND('Lic-Misc'!I11,0) -> 0
B10: Support Services | C10: =Support!H11 -> 0
B11: Managed Services | C11: =Support!H23 -> 0
B12: Cloud Infrastructure Cost | C12: =Hardware!I7 -> 0
B14: Total Revenue | C14: =SUM(C5:C10) -> 0
B15: SST 8% | C15: =C14*0.08 -> 0
B16: Total Revenue Included SST | C16: =SUM(C14:C15) -> 0
B18: Cost | C18: RM
B19: Implementation
B20: Developer-1
B21: Developer-2
B22: Business Analyst
B23: Project Manager
B24: Solution Architect
B25: Project Director
B26: License -UiPath | C26: ='Lic-UiPath'!J11 -> 0
B27: License -Microsoft | C27: ='Lic-Misc'!G11 -> 0
B28: License -Cyclone | C28: ='Lic-Cyc'!G11 -> 0
B29: Support
B30: AI Tools
B31: Developer
B32: Support Manager
B33: Travel
B34: Total Cost
B36: Total Profit | C36: =C14-C34 -> 0
B37: Total Margin % | C37: =C36/C14 -> #DIV/0!
B38: Project Incentive | C38: =C36*10% -> 0

Sheet Project Details
B2: Project Details
B4: Items | C4: Project Information | D4: Remarks
B5: Project ID | C5: COG0000000 | D5: Please refer in acumatica CRM - Opportunity ID Number
B6: Customer Name | C6: Jabatan Akauntan Negara Malaysia | D6: Please refer in acumatica CRM
B7: Project Name 1 | C7: Automation of WTD | D7: Examples
B8: Project Name 2 | C8: Automation of WTD 1 | D8: Examples
B9: Project Name 3 | C9: Automation of WTD 2 | D9: Examples
B10: Project Name 4 | C10: Automation of WTD 3 | D10: Examples
B11: Project Name 5 | C11: Automation of WTD 4 | D11: Examples
B13: Items | C13: Project Mandays
B14: AI Developer | C14: ='Project Cost-01'!R11 -> 0
B15: RPA Developer 1 | C15: ='Project Cost-01'!R9 -> 0
B16: RPA Developer 2 | C16: ='Project Cost-01'!R10 -> 0
B17: Business Analyst | C17: ='Project Cost-01'!R8 -> 0
B18: Project Manager | C18: ='Project Cost-01'!R6 -> 0
B19: Solution Architect | C19: ='Project Cost-01'!R7 -> 0
B20: Project Director | C20: ='Project Cost-01'!R5 -> 0
B21: Support | C21: =Support!G11 -> 72

Sheet Project Cost-01
B1: Process Name | C1: ='Project Details'!C7 -> Automation of WTD
B4: Roles | C4: Grade | D4: Man-day rate (RM) | E4: Discount | F4: Discounted Man-days rate | G4: W1 | H4: W2 | I4: W3 | J4: W4 | K4: W5 | L4: W6 | M4: W7 | N4: W8 | O4: W7 | P4: W8 | Q4: W9 - 12 | R4: Estimated no. of days | S4: Estimated market fee | T4: Discount | U4: Discounted consulting fee
B5: Project Director | C5: Director | D5: ='Master File'!C8 -> 2500 | F5: =D5-E5 -> 2500 | R5: =SUM(G5:P5) -> 0 | S5: =F5*R5 -> 0 | T5: 0 | U5: =S5*(1-T5) -> 0
B6: Project manager | C6: Manager | D6: ='Master File'!C9 -> 2000 | F6: =D6-E6 -> 2000 | R6: =SUM(G6:P6) -> 0 | S6: =F6*R6 -> 0 | T6: 0 | U6: =S6*(1-T6) -> 0
B7: Solution Architect | C7: Manager | D7: ='Master File'!C11 -> 1800 | F7: =D7-E7 -> 1800 | R7: =SUM(G7:Q7) -> 0 | S7: =F7*R7 -> 0 | T7: 0 | U7: =S7*(1-T7) -> 0
B8: Business Analyst | C8: Associate | D8: ='Master File'!C12 -> 1500 | F8: =D8-E8 -> 1500 | R8: =SUM(G8:P8) -> 0 | S8: =F8*R8 -> 0 | T8: 0 | U8: =S8*(1-T8) -> 0
B9: RPA Developer 1 | C9: Associate | D9: ='Master File'!C13 -> 1500 | F9: =D9-E9 -> 1500 | R9: =SUM(G9:Q9) -> 0 | S9: =F9*R9 -> 0 | T9: 0 | U9: =S9*(1-T9) -> 0
B10: RPA Developer 2 | C10: Associate | D10: ='Master File'!C13 -> 1500 | F10: =D10-E10 -> 1500 | R10: =SUM(G10:Q10) -> 0 | S10: =F10*R10 -> 0 | T10: 0 | U10: =S10*(1-T10) -> 0
B11: AI Developer | C11: Associate | D11: ='Master File'!C10 -> 1800 | F11: =D11-E11 -> 1800 | R11: =SUM(G11:P11) -> 0 | S11: =F11*R11 -> 0 | T11: 0 | U11: =S11*(1-T11) -> 0
G13: Process Assessment & PDD | H13: Configuration of robot process | O13: UAT/Handover & Go-Live | Q13: Warranty Period | R13: =SUM(R5:R11) -> 0 | S13: =SUM(S5:S11) -> 0 | U13: =SUM(U5:U11) -> 0
B15: Total fee | D15: =U13 -> 0
B16: OPE | E16: 100 per week/developer
B17: Total Fee + OPE (excluding of Taxes) | D17: =D15+D16 -> 0
B19: Blended Man-Day Rate | D19: =U13/R13 -> #DIV/0!

Sheet Lic-UiPath
C1: UiPath License
B2: No. | C2: Product Name | D2: List Price (US$) | E2: Qty | F2: Total List Price (US$) | G2: Total List Price (RM) | H2: Discount to Cognitive (%) | I2: Total Discounted Price (USD) | J2: Cognitve's Cost Price (RM) | K2: Discount to Client fm List Price (%) | L2: Price to Client (RM) | M2: Price to Client (RM)SST 8% | N2: Cognitive's Margin (RM) | O2: Cognitive's Margin (%)
B3: 1 | C3: UiPath - Flex - Automation Developer - Named User | D3: 4400 | F3: =D3*E3 -> 0 | G3: =F3*$D$13 -> 0 | H3: 0.2 | I3: =F3*(1-H3) -> 0 | J3: =G3*(1-H3) -> 0 | K3: 0.075 | L3: =G3*(1-K3) -> 0 | M3: =L3*1.08 -> 0 | N3: =L3-J3 -> 0 | O3: =N3/L3 -> #DIV/0!
B4: 3 | C4: UiPath - Flex - Unattended Robot | D4: 10000 | F4: =D4*E4 -> 0 | G4: =F4*$D$13 -> 0 | H4: 0.2 | I4: =F4*(1-H4) -> 0 | J4: =G4*(1-H4) -> 0 | K4: 0.075 | L4: =G4*(1-K4) -> 0 | M4: =L4*1.08 -> 0 | N4: =L4-J4 -> 0 | O4: =N4/L4 -> #DIV/0!
B5: 4 | C5: UiPath - Flex - Unattended Robot - Test | D5: 2000 | F5: =D5*E5 -> 0 | G5: =F5*$D$13 -> 0 | H5: 0.2 | I5: =F5*(1-H5) -> 0 | J5: =G5*(1-H5) -> 0 | K5: 0.05 | L5: =G5*(1-K5) -> 0 | M5: =L5*1.08 -> 0 | N5: =L5-J5 -> 0 | O5: =N5/L5 -> #DIV/0!
B6: 5 | C6: UiPath - Flex - Automation Hub | D6: 15000 | F6: =D6*E6 -> 0 | G6: =F6*$D$13 -> 0 | H6: 0.2 | I6: =F6*(1-H6) -> 0 | J6: =G6*(1-H6) -> 0 | K6: 0.05 | L6: =G6*(1-K6) -> 0 | M6: =L6*1.08 -> 0 | N6: =L6-J6 -> 0 | O6: =N6/L6 -> #DIV/0!
B7: 6 | C7: UiPath - Flex - AI Unit Bundle - 60K | D7: 12000 | F7: =D7*E7 -> 0 | G7: =F7*$D$13 -> 0 | H7: 0.2 | I7: =F7*(1-H7) -> 0 | J7: =G7*(1-H7) -> 0 | K7: 0.075 | L7: =G7*(1-K7) -> 0 | M7: =L7*1.08 -> 0 | N7: =L7-J7 -> 0 | O7: =N7/L7 -> #DIV/0!
B8: 7 | C8: UiPath - Flex - Citizen Developer - Named User | D8: 2600 | F8: =D8*E8 -> 0 | G8: =F8*$D$13 -> 0 | H8: 0.1 | I8: =F8*(1-H8) -> 0 | J8: =G8*(1-H8) -> 0 | K8: 0 | L8: =G8*(1-K8) -> 0 | M8: =L8*1.08 -> 0 | N8: =L8-J8 -> 0 | O8: =N8/L8 -> #DIV/0!
B9: 8 | C9: UiPath - Flex - Action Center - Named User | D9: 200 | F9: =D9*E9 -> 0 | G9: =F9*$D$13 -> 0 | H9: 0.1 | I9: =F9*(1-H9) -> 0 | J9: =G9*(1-H9) -> 0 | K9: 0 | L9: =G9*(1-K9) -> 0 | M9: =L9*1.08 -> 0 | N9: =L9-J9 -> 0 | O9: =N9/L9 -> #DIV/0!
C11: Total | F11: =SUM(F3:F9) -> 0 | G11: =SUM(G3:G9) -> 0 | I11: =SUM(I3:I9) -> 0 | J11: =SUM(J3:J9) -> 0 | L11: =SUM(L3:L9) -> 0 | M11: =SUM(M3:M9) -> 0 | N11: =SUM(N3:N9) -> 0 | O11: =N11/L11 -> #DIV/0!
C13: US$ to RM conversion rate : | D13: =ROUND(D14,2) -> 4.16
C14: Updated 23/4/2025 | D14: 4.158 | L14: =L4/2 -> 0

Sheet Lic-Misc
B3: No. | C3: Product Name | D3: Unit | E3: Month | F3: Unit Price (RM) | G3: Cognitive's Cost Price (RM) | H3: Cognitive's Mark up (RM) | I3: Price to Client (RM) | J3: SST 8% | K3: Price to Client (RM) with SST | L3: Cognitive's Margin (RM) | M3: Cognitive's Margin (%)
B4: 1 | C4: Power Automate Premium | E4: 12 | F4: =E4*$D$13*1 -> 49.92 | G4: =D4*F4 -> 0 | H4: 0.1 | I4: =G4*(1+H4) -> 0 | J4: =I4*0.08 -> 0 | K4: =I4*1.08 -> 0 | L4: =I4-G4 -> 0 | M4: =L4/G4 -> #DIV/0!
B5: 2 | C5: Power Automate Process | E5: 12 | F5: =E5*$D$13*1 -> 49.92 | G5: =D5*F5 -> 0 | H5: 0.1 | I5: =G5*(1+H5) -> 0 | J5: =I5*0.08 -> 0 | K5: =I5*1.08 -> 0 | L5: =I5-G5 -> 0 | M5: =L5/G5 -> #DIV/0!
B6: 3 | C6: Power Automate Process | E6: 12 | F6: =E6*$D$13*1 -> 49.92 | G6: =D6*F6 -> 0 | H6: 0.1 | I6: =G6*(1+H6) -> 0 | J6: =I6*0.08 -> 0 | K6: =I6*1.08 -> 0 | L6: =I6-G6 -> 0 | M6: =L6/G6 -> #DIV/0!
B7: 4 | C7: Power BI Pro | E7: 12 | F7: =E7*$D$13*1 -> 49.92 | G7: =D7*F7 -> 0 | H7: 0.1 | I7: =G7*(1+H7) -> 0 | J7: =I7*0.08 -> 0 | K7: =I7*1.08 -> 0 | L7: =I7-G7 -> 0 | M7: =L7/G7 -> #DIV/0!
B8: 5 | C8: Power Bi Premium | E8: 12 | F8: =E8*$D$13*1 -> 49.92 | G8: =D8*F8 -> 0 | H8: 0.1 | I8: =G8*(1+H8) -> 0 | J8: =I8*0.08 -> 0 | K8: =I8*1.08 -> 0 | L8: =I8-G8 -> 0 | M8: =L8/G8 -> #DIV/0!
B9: 4 | C9: Microsoft - Azure Custom (Commitment 20K pages) | E9: 12 | F9: =E9*$D$13*540 -> 26956.8 | G9: =D9*F9 -> 0 | H9: 0.1 | I9: =G9*(1+H9) -> 0 | J9: =I9*0.08 -> 0 | K9: =I9*1.08 -> 0 | L9: =I9-G9 -> 0 | M9: =L9/G9 -> #DIV/0! | N9: =SUM(I9:I10) -> 0 | O9: =0.08*N9 -> 0
B10: 5 | C10: Microsoft - Azure Custom (Overage 17k pages) | E10: 12 | G10: =D10*F11*E10 -> 0 | H10: 0.1 | I10: =G10*(1+H10) -> 0 | J10: =I10*0.08 -> 0 | K10: =I10*1.08 -> 0 | L10: =I10-G10 -> 0 | M10: =L10/G10 -> #DIV/0!
C11: Total | F11: =D10*E10*$D$13*1 -> 0 | G11: =SUM(G4:G10) -> 0 | I11: =G11*(1+H11) -> 0 | J11: =I11*0.08 -> 0 | K11: =I11*1.08 -> 0 | L11: =I11-G11 -> 0 | M11: =L11/G11 -> #DIV/0!
C13: US$ to RM conversion rate : | D13: =ROUND(D14,2) -> 4.16
C14: Updated 23/4/2025 | D14: ='Lic-UiPath'!D14 -> 4.158

Sheet Lic-Cyc
C1: Cyclone License
B2: No. | C2: Product Name | D2: Qty | E2: Total List Price (RM) | F2: Discount to Cognitive (%) | G2: Cognitve's Cost Price (RM) | H2: Discount to Client fm List Price (%) | I2: Price to Client (RM) | J2: Price to Client (RM)SST 8% | K2: Cognitive's Margin (RM) | L2: Cognitive's Margin (%)
B3: 1 | C3: Cyclone - Attended Robot | E3: 7200 | F3: 0.35 | G3: =D3*E3*(1-F3) -> 0 | H3: 0 | I3: =D3*E3*(1-H3) -> 0 | J3: =I3*1.08 -> 0 | K3: =I3-G3 -> 0 | L3: =K3/I3 -> #DIV/0!
B4: 2 | C4: Cyclone - Unattended Robot | E4: 15750 | F4: 0.35 | G4: =D4*E4*(1-F4) -> 0 | H4: 0 | I4: =D4*E4*(1-H4) -> 0 | J4: =I4*1.08 -> 0 | K4: =I4-G4 -> 0 | L4: =K4/I4 -> #DIV/0!
B5: 3 | C5: Cyclone - Intelligent Document Processing (60k) | E5: 24000 | F5: 0.35 | G5: =D5*E5*(1-F5) -> 0 | H5: 0 | I5: =D5*E5*(1-H5) -> 0 | J5: =I5*1.08 -> 0 | K5: =I5-G5 -> 0 | L5: =K5/I5 -> #DIV/0!
B6: 4 | C6: Clyclone - Designer | E6: 18000 | F6: 0.35 | G6: =D6*E6*(1-F6) -> 0 | H6: 0 | I6: =D6*E6*(1-H6) -> 0 | J6: =I6*1.08 -> 0 | K6: =I6-G6 -> 0 | L6: =K6/I6 -> #DIV/0!
B7: 5 | C7: Cyclone - Unattended Robot-Test | E7: 4500 | F7: 0.35 | G7: =D7*E7*(1-F7) -> 0 | H7: 0 | I7: =D7*E7*(1-H7) -> 0 | J7: =I7*1.08 -> 0 | K7: =I7-G7 -> 0 | L7: =K7/I7 -> #DIV/0!
B8: 6 | C8: Cyclone - COE | E8: 400000 | F8: 0.35 | G8: =D8*E8*(1-F8) -> 0 | H8: 0 | I8: =D8*E8*(1-H8) -> 0 | J8: =I8*1.08 -> 0 | K8: =I8-G8 -> 0 | L8: =K8/I8 -> #DIV/0!
B9: 7 | C9: Cyclone - Controller | E9: 60000 | F9: 0.35 | G9: =D9*E9*(1-F9) -> 0 | H9: 0 | I9: =D9*E9*(1-H9) -> 0 | J9: =I9*1.08 -> 0 | K9: =I9-G9 -> 0 | L9: =K9/I9 -> #DIV/0!
C11: Total | G11: =SUM(G3:G10) -> 0 | I11: =SUM(I3:I10) -> 0 | J11: =SUM(J3:J10) -> 0 | K11: =SUM(K3:K9) -> 0 | L11: =K11/I11 -> #DIV/0!
D16: Qty | E16: Difference
B17: 1 | C17: UiPath - Automation Developer - Named User | D17: 1 | E17: =(I3-#REF!)/#REF! -> #REF!
B18: 2 | C18: UiPath - Attended Robot - Named User | D18: 1 | E18: =(#REF!-#REF!)/#REF! -> #REF!
C19: Total

Sheet Support
B1: FY26 - Cognitive Consulting's Support Rate Card
B3: Grade | C3: Man-day rate (RM)
B4: Director | C4: 2000
B5: Support Manager | C5: 1500
B6: RPA Support | C6: 1200
B7: External | C7: 1500
B9: Basic Support
B10: Items | C10: Resources | D10: Manday Rate | E10: Discount Manday Rate | F10: Total Manday Rate | G10: # of Days per year | H10: Total
B11: Basic Support | C11: 0 | D11: 1200 | E11: 300 | F11: =D11-E11 -> 900 | G11: =(3+2+1)*12 -> 72 | H11: =(F11*G11*C11) -> 0
B12: SST 8% | H12: =H11*0.08 -> 0
B13: Total | H13: =SUM(H11:H12) -> 0
B16: Managed Services
B17: Service | C17: Resources | D17: Manday Rate | E17: Discount Manday Rate | F17: Total Manday Rate | G17: # of Days per year | H17: Total
B18: =B6 -> RPA Support | C18: 0 | D18: =C6 -> 1200 | F18: =D18-E18 -> 1200 | G18: 0 | H18: =(D18*G18) -> 0
B19: =B5 -> Support Manager | C19: 0 | D19: =C5 -> 1500 | F19: =D19-E19 -> 1500 | G19: 0 | H19: =(D19*G19) -> 0
B20: =B4 -> Director | D20: =C4 -> 2000 | F20: =D20-E20 -> 2000 | H20: =(D20*G20) -> 0
B21: =B7 -> External | D21: =C7 -> 1500 | F21: =D21-E21 -> 1500 | H21: =(D21*G21) -> 0
B23: Total | H23: =SUM(H18:H20) -> 0
B24: SST 8% | H24: =H18*0.08 -> 0
B25: Grand total | H25: =SUM(H23:H24) -> 0
G27: Total with SST | H27: =H11+H12 -> 0
C29: =18900/7/900 -> 3
C32: 2024 | D32: 2025
B33: PSDD | C33: =3*7 -> 21 | D33: =3*12 -> 36
B34: JIM RECON/FINBOT | C34: =2*12 -> 24 | D34: =2*12 -> 24
B35: DeRantau | C35: =1*12 -> 12 | D35: =1*12 -> 12
B36: Total Mandays | C36: =SUM(C33:C35) -> 57 | D36: =SUM(D33:D35) -> 72
B37: Mandays Rate | C37: 900 | D37: 900
B38: Total Price | C38: =C36*C37 -> 51300 | D38: =D36*D37 -> 64800
B39: Discount | C39: -400 | D39: -800
B40: Final Price | C40: =C38+C39 -> 50900 | D40: =D38+D39 -> 64000

Sheet Master File
B2: Project Master Data
B5: FY26 - Cognitive Consulting's Rate Card
B7: Grade | C7: Man-day rate (RM)
B8: Director | C8: 2500
B9: Manager/Solution Arch | C9: 2000
B10: Senior AI Associate | C10: 1800
B11: Senior Associate | C11: 1800
B12: Business Analyst | C12: 1500
B13: RPA Associate | C13: 1500
B14: External | C14: 2000
B16: Internal Costing
B17: Grade | C17: RM | D17: Discount Pricing | E17: Total | F17: Per Days
B18: AI Developer | C18: =5000*1.3 -> 6500 | E18: =C18-D18 -> 6500 | F18: =E18/14 -> 464.28571
B19: RPA Developer | C19: =3500*1.3 -> 4550 | E19: =C19-D19 -> 4550 | F19: =E19/14 -> 325
B20: Senior RPA Developer | C20: =5500*1.3 -> 7150 | E20: =C20-D20 -> 7150 | F20: =E20/14 -> 510.71429
B21: Business Analyst | C21: =5000*1.3 -> 6500 | E21: =C21-D21 -> 6500 | F21: =E21/14 -> 464.28571
B22: Project Manager | C22: =8000*1.3 -> 10400 | E22: =C22-D22 -> 10400 | F22: =E22/14 -> 742.85714
B23: Solution Architect | C23: =8000*1.3 -> 10400 | E23: =C23-D23 -> 10400 | F23: =E23/14 -> 742.85714
B24: Project Director | C24: =20000*1.3 -> 26000 | E24: =C24-D24 -> 26000 | F24: =E24/14 -> 1857.1429
B25: External | C25: 2500 | E25: =C25-D25 -> 2500 | F25: =E25/14 -> 178.57143

Sheet Internal
B2: Project Master Data
B4: Items | C4: Project Information | D4: Remarks
B5: Project ID | C5: ='Project Details'!C5 -> COG0000000 | D5: Please refer in acumatica CRM
B6: Customer Name | C6: Jabatan Akauntan Negara Malaysia | D6: Please refer in acumatica CRM
B7: Short Customer Name | C7: JANM | D7: Please refer in acumatica CRM
B8: Project Name | C8: Automation of WTD | D8: This information need to link with Project costing
B10: Items | C10: Project Mandays | D10: Project Hours | E10: Mandays Rate | F10: Job code | G10: Remarks
B11: AI Developer | C11: =(2*8) -> 16 | F11: JANM-WTD-DEV | G11: This information need to link with Project costing
B12: RPA Developer | C12: =(2*8) -> 16 | F12: JANM-WTD-DEV1 | G12: This information need to link with Project costing
B13: Business Analyst | C13: =(2*8) -> 16 | F13: JANM-WTD-BA | G13: This information need to link with Project costing
B14: Project Manager | C14: =(2*8) -> 16 | F14: JANM-WTD-PM | G14: This information need to link with Project costing
B15: Solution Architect | C15: =(2*8) -> 16 | F15: JANM-WTD-SA | G15: This information need to link with Project costing
B16: Project Director | C16: =(2*8) -> 16 | G16: This information need to link with Project costing
B17: Support | C17: =(2*8) -> 16 | F17: JANM-WTD-SUP | G17: This information need to link with Project costing
B19: Grade | C19: Man-day rate (RM)
B20: Director | C20: 2500
B21: Manager | C21: 1800
B22: Senior Associate | C22: 1500
B23: Business Analyst | C23: 1300
B24: AI Associate | C24: 1500
B25: RPA Associate | C25: 1200
B26: External | C26: 2000
B28: Grade Internal Cost | C28: RM
B29: AI Developer | C29: =4500*1.3 -> 5850
B30: RPA Developer | C30: =3500*1.3 -> 4550
B31: Senior RPA Developer | C31: =4500*1.3 -> 5850
B32: Business Analyst | C32: =5000*1.3 -> 6500
B33: Project Manager | C33: =7000*1.3 -> 9100
B34: Solution Architect | C34: =7000*1.3 -> 9100
B35: Project Director | C35: =10000*1.3 -> 13000

Sheet Hardware
C2: Cloud
B3: No. | C3: Product Name | D3: Unit | E3: Month | F3: Unit Price (RM) | G3: Cognitive's Cost Price (RM) | H3: Cognitive's Mark up (RM) | I3: Price to Client (RM) | J3: SST 8% | K3: Price to Client (RM) with SST | L3: Cognitive's Margin (RM) | M3: Cognitive's Margin (%)
B4: 1 | D4: 0 | E4: 0 | G4: =E4*F4*D4 -> 0 | H4: 0.2 | I4: =G4*(1+H4) -> 0 | J4: =I4*0.08 -> 0 | K4: =I4*1.08 -> 0 | L4: =I4-G4 -> 0 | M4: =L4/G4 -> #DIV/0!
B5: 2 | E5: 0 | G5: =E5*F5*D5 -> 0 | H5: 0.2 | I5: =G5*(1+H5) -> 0 | J5: =I5*0.08 -> 0 | K5: =I5*1.08 -> 0 | L5: =I5-G5 -> 0 | M5: =L5/G5 -> #DIV/0!
B6: 3 | E6: 0 | G6: =E6*F6*D6 -> 0 | H6: 0.2 | I6: =G6*(1+H6) -> 0 | J6: =I6*0.08 -> 0 | K6: =I6*1.08 -> 0 | L6: =I6-G6 -> 0 | M6: =L6/G6 -> #DIV/0! | N6: =SUM(I6:I6) -> 0 | O6: =0.08*N6 -> 0
C7: Total | G7: =SUM(G4:G6) -> 0 | I7: =SUM(I4:I6) -> 0 | J7: =SUM(J4:J6) -> 0 | K7: =SUM(K4:K6) -> 0 | L7: =SUM(L4:L6) -> 0 | M7: =L7/G7 -> #DIV/0!
